{
  "instructors": [
    {
      "id": 1,
      "name": "i2",
      "avatar_url": "https://images.unsplash.com/photo-1547919307-1ecb10702e6f?ixlib=rb-1.2.1&ixid=eyJhcHBfaWQiOjEyMDd9&auto=format&fit=crop&w=334&q=80",
      "birth": 978307200000,
      "gender": "M",
      "services": " d",
      "created_at": 1582937569720
    },
    {
      "id": 2,
      "name": "i3",
      "avatar_url": "https://images.unsplash.com/photo-1547919307-1ecb10702e6f?ixlib=rb-1.2.1&ixid=eyJhcHBfaWQiOjEyMDd9&auto=format&fit=crop&w=334&q=80",
      "birth": 982886400000,
      "gender": "M",
      "services": "d",
      "created_at": 1582937621308
    },
    {
      "id": 3,
      "name": "i4",
      "avatar_url": "http://google.com",
      "birth": 981072000000,
      "gender": "M",
      "services": "fkjdf",
      "created_at": 1582937647317
    }
  ],
  "members": [
    {
      "id": 1,
      "name": "m1",
      "avatar_url": "https://images.unsplash.com/photo-1547919307-1ecb10702e6f?ixlib=rb-1.2.1&ixid=eyJhcHBfaWQiOjEyMDd9&auto=format&fit=crop&w=334&q=80",
      "birth": 1000425600000,
      "gender": "M",
      "email": "m1@gmail.com",
      "blood": "B1",
      "weight": "50",
      "height": "180"
    },
    {
      "id": 2,
      "name": "m1",
      "avatar_url": "https://images.unsplash.com/photo-1547919307-1ecb10702e6f?ixlib=rb-1.2.1&ixid=eyJhcHBfaWQiOjEyMDd9&auto=format&fit=crop&w=334&q=80",
      "birth": 1000425600000,
      "gender": "M",
      "email": "m1@gmail.com",
      "blood": "AB0",
      "weight": "50",
      "height": "189"
    },
    {
      "id": 3,
      "name": "m2",
      "avatar_url": "https://images.unsplash.com/photo-1547919307-1ecb10702e6f?ixlib=rb-1.2.1&ixid=eyJhcHBfaWQiOjEyMDd9&auto=format&fit=crop&w=334&q=80",
      "birth": 1000425600000,
      "gender": "M",
      "email": "m1@gmail.com",
      "blood": "B-",
      "weight": "400",
      "height": "183"
    }
  ]
}